{
  "bg": "https://raw.githubusercontent.com/gabriel-brasil/thesimpsonsquiz/main/src/images/bg-main.jpg",
  "title": "The Simpsons Quiz",
  "description": "Teste os seus conhecimentos sobre The Simpsons e vamos ver o quanto você é um amarelão!",
  "questions": [
    {
      "image": "https://raw.githubusercontent.com/gabriel-brasil/thesimpsonsquiz/main/src/quizImages/question1.jpg",
      "title": "Qual o nome do irmão gêmeo de Bart Simpson?",
      "description": "Dica: Ele apareceu em um episódio de dia das Bruxas.",
      "answer": 0,
      "alternatives": [
        "Hugo Bouvier Simpson",
        "Bill Simpson",
        "Orville Bouvier Simpson",
        "Arthur Simpson"
      ]
    },
    {
      "image": "https://raw.githubusercontent.com/gabriel-brasil/thesimpsonsquiz/main/src/quizImages/question2.jpg",
      "title": "Por quem a Lisa Simpson nunca se apaixonou?",
      "description": "Dia: Lisa recebe um cartão de dia dos namorados, mas ela não sente o mesmo.",
      "answer": 1,
      "alternatives": [
        "Nelson Muntz",
        "Ralph Wiggum",
        "Luke Stetson",
        "Colin"
      ]
    },
    {
      "image": "https://raw.githubusercontent.com/gabriel-brasil/thesimpsonsquiz/main/src/quizImages/question3.jpg",
      "title": "Qual o nome de solteira de Marge Simpson?",
      "description": "Dica: Em um episódio, Lisa ameaça Homer dizendo que trocaria seu sobrenome Simpson pelo nome de solteira de Marge.",
      "answer": 3,
      "alternatives": [
        "Gurney ",
        "Jay",
        "Billout",
        "Bouvier "
      ]
    },
    {
      "image": "https://raw.githubusercontent.com/gabriel-brasil/thesimpsonsquiz/main/src/quizImages/question4.jpg",
      "title": "Qual objeto foi descoberto dentro da cabeça de Homer Simpson?",
      "description": "Dica: Em um Raio-X, Homer descobre que havia algo dentro de sua cabeça. Algo que ele mesmo tinha colocado.",
      "answer": 0,
      "alternatives": [
        "Crayon",
        "Moeda",
        "Caneta",
        "Soldadinho de brinquedo"
      ]
    },
    {
      "image": "https://raw.githubusercontent.com/gabriel-brasil/thesimpsonsquiz/main/src/quizImages/question5.jpg",
      "title": "Em quem Maggie Simpson atirou com uma arma?",
      "description": "Dica: Maggie estava sendo roubada quando acidentalmente disparou a arma.",
      "answer": 2,
      "alternatives": [
        "Sideshow Bob",
        "Krusty",
        "Montgomery Burns",
        "Moe Szyslak"
      ]
    }
  ],
  "external": [
    "https://color-theory-quiz.dafinysouza.vercel.app/"
  ],
  "theme": {
    "colors": {
      "primary": {
        "light": "#4dabf5",
        "main": "#03a9f4",
        "dark": "#1769aa"
      },
      "secondary": {
        "light": "#ffdd4b",
        "main": "#ffd51f",
        "dark": "#b29515"
      },
      "mainBgDark": "#333333",
      "mainBgLight": "#FFFFFF",
      "contrastText": "#FFFFFF",
      "contrastTextDark": "#333333",
      "wrong": "#e24c66",
      "success": "#4CAF50"
    },
    "borderRadius": "4px"
  }
}